{
  "openapi": "3.0.1",
  "info": {
    "title": "task12_api",
    "version": "2025-04-08T08:49:16Z"
  },
  "servers": [
    {
      "url": "https://sqtcfxr1fk.execute-api.eu-west-1.amazonaws.com/{basePath}",
      "variables": {
        "basePath": {
          "default": "api"
        }
      }
    }
  ],
  "paths": {
    "/reservations": {
      "get": {
        "summary": "Get all reservations",
        "description": "This endpoint returns all existing reservations in the system, including details such as table number, client name, contact information, reservation date, and time slot.",
        "responses": {
          "200": {
            "description": "A list of reservations got successfully",
            "content": {
              "application/json": {
                "schema": {
                  "$ref": "#/components/schemas/Empty"
                }
              }
            }
          }
        },
        "security": [
          {
            "authorizer": []
          }
        ],
        "x-amazon-apigateway-integration": {
          "httpMethod": "POST",
          "uri": "arn:aws:apigateway:eu-west-1:lambda:path/2015-03-31/functions/arn:aws:lambda:eu-west-1:423623856894:function:api_handler/invocations",
          "responses": {
            "default": {
              "statusCode": "200"
            }
          },
          "passthroughBehavior": "when_no_match",
          "type": "aws_proxy"
        }
      },
      "post": {
        "summary": "Create a new reservation",
        "description": "This endpoint allows a user to create a new reservation by providing details such as table ID, client name, contact information, date, and time slot.",
        "requestBody": {
          "required": true,
          "content": {
            "application/json": {
              "schema": {
                "type": "object",
                "properties": {
                  "tableId": {
                    "type": "string",
                    "description": "Identifier of the table being reserved"
                  },
                  "clientName": {
                    "type": "string",
                    "description": "Full name of the person placing the reservation"
                  },
                  "contactInfo": {
                    "type": "string",
                    "description": "Client’s contact details, such as phone number or email address"
                  },
                  "date": {
                    "type": "string",
                    "format": "date",
                    "description": "Date on which the reservation is scheduled"
                  },
                  "timeSlot": {
                    "type": "string",
                    "description": "Reserved time window (e.g., '18:00-20:00')"
                  }
                },
                "required": [
                  "tableId",
                  "clientName",
                  "date",
                  "timeSlot"
                ]
              }
            }
          }
        },
        "responses": {
          "200": {
            "description": "Reservation created successfully",
            "content": {
              "application/json": {
                "schema": {
                  "$ref": "#/components/schemas/Empty"
                }
              }
            }
          }
        },
        "security": [
          {
            "authorizer": []
          }
        ],
        "x-amazon-apigateway-integration": {
          "httpMethod": "POST",
          "uri": "arn:aws:apigateway:eu-west-1:lambda:path/2015-03-31/functions/arn:aws:lambda:eu-west-1:423623856894:function:api_handler/invocations",
          "responses": {
            "default": {
              "statusCode": "200"
            }
          },
          "passthroughBehavior": "when_no_match",
          "type": "aws_proxy"
        }
      }
    },
    "/tables": {
      "get": {
        "summary": "Retrieve all tables",
        "description": "This endpoint returns a list of all tables registered in the system, along with their IDs and additional related information.",
        "responses": {
          "200": {
            "description": "A list of tables retrieved successfully",
            "headers": {
              "Access-Control-Allow-Origin": {
                "schema": {
                  "type": "string"
                }
              }
            },
            "content": {
              "application/json": {
                "schema": {
                  "$ref": "#/components/schemas/Empty"
                }
              }
            }
          }
        },
        "security": [
          {
            "authorizer": []
          }
        ],
        "x-amazon-apigateway-integration": {
          "httpMethod": "POST",
          "uri": "arn:aws:apigateway:eu-west-1:lambda:path/2015-03-31/functions/arn:aws:lambda:eu-west-1:423623856894:function:api_handler/invocations",
          "responses": {
            "default": {
              "statusCode": "200",
              "responseParameters": {
                "method.response.header.Access-Control-Allow-Origin": "'*'"
              }
            }
          },
          "passthroughBehavior": "when_no_match",
          "type": "aws_proxy"
        }
      },
      "post": {
        "summary": "Create a new table",
        "description": "This endpoint allows the creation of a new table by specifying its details, such as table ID and capacity.",
        "requestBody": {
          "required": true,
          "content": {
            "application/json": {
              "schema": {
                "type": "object",
                "properties": {
                  "tableId": {
                    "type": "string",
                    "description": "A unique ID assigned to the table"
                  },
                  "capacity": {
                    "type": "integer",
                    "description": "Number of guests the table is designed to seat"
                  }
                },
                "required": [
                  "tableId",
                  "capacity"
                ]
              }
            }
          }
        },
        "responses": {
          "200": {
            "description": "Table created successfully",
            "headers": {
              "Access-Control-Allow-Origin": {
                "schema": {
                  "type": "string"
                }
              }
            },
            "content": {
              "application/json": {
                "schema": {
                  "$ref": "#/components/schemas/Empty"
                }
              }
            }
          }
        },
        "security": [
          {
            "authorizer": []
          }
        ],
        "x-amazon-apigateway-integration": {
          "httpMethod": "POST",
          "uri": "arn:aws:apigateway:eu-west-1:lambda:path/2015-03-31/functions/arn:aws:lambda:eu-west-1:423623856894:function:api_handler/invocations",
          "responses": {
            "default": {
              "statusCode": "200",
              "responseParameters": {
                "method.response.header.Access-Control-Allow-Origin": "'*'"
              }
            }
          },
          "passthroughBehavior": "when_no_match",
          "type": "aws_proxy"
        }
      },
      "options": {
        "summary": "CORS preflight for /tables",
        "description": "Handles CORS preflight requests for the /tables endpoint.",
        "responses": {
          "200": {
            "description": "CORS preflight response",
            "headers": {
              "Access-Control-Allow-Origin": {
                "schema": {
                  "type": "string"
                }
              },
              "Access-Control-Allow-Methods": {
                "schema": {
                  "type": "string"
                }
              },
              "Access-Control-Allow-Headers": {
                "schema": {
                  "type": "string"
                }
              }
            },
            "content": {
              "application/json": {
                "schema": {
                  "$ref": "#/components/schemas/Empty"
                }
              }
            }
          }
        },
        "x-amazon-apigateway-integration": {
          "responses": {
            "default": {
              "statusCode": "200",
              "responseParameters": {
                "method.response.header.Access-Control-Allow-Methods": "'*'",
                "method.response.header.Access-Control-Allow-Headers": "'Content-Type,X-Amz-Date,Authorization,X-Api-Key,X-Amz-Security-Token'",
                "method.response.header.Access-Control-Allow-Origin": "'*'"
              }
            }
          },
          "requestTemplates": {
            "application/json": "{\"statusCode\": 200}"
          },
          "passthroughBehavior": "when_no_match",
          "type": "mock"
        }
      }
    },
    "/signin": {
      "post": {
        "summary": "Sign in a user",
        "description": "This endpoint authenticates a user by accepting their username and password, returning an authentication token upon success.",
        "requestBody": {
          "required": true,
          "content": {
            "application/json": {
              "schema": {
                "type": "object",
                "properties": {
                  "username": {
                    "type": "string",
                    "description": "The username of the user"
                  },
                  "password": {
                    "type": "string",
                    "description": "The password of the user"
                  }
                },
                "required": [
                  "username",
                  "password"
                ]
              }
            }
          }
        },
        "responses": {
          "200": {
            "description": "User signed in successfully",
            "headers": {
              "Access-Control-Allow-Origin": {
                "schema": {
                  "type": "string"
                }
              }
            },
            "content": {
              "application/json": {
                "schema": {
                  "$ref": "#/components/schemas/Empty"
                }
              }
            }
          }
        },
        "x-amazon-apigateway-integration": {
          "httpMethod": "POST",
          "uri": "arn:aws:apigateway:eu-west-1:lambda:path/2015-03-31/functions/arn:aws:lambda:eu-west-1:423623856894:function:api_handler/invocations",
          "responses": {
            "default": {
              "statusCode": "200",
              "responseParameters": {
                "method.response.header.Access-Control-Allow-Origin": "'*'"
              }
            }
          },
          "passthroughBehavior": "when_no_match",
          "type": "aws_proxy"
        }
      },
      "options": {
        "responses": {
          "200": {
            "description": "CORS preflight response",
            "headers": {
              "Access-Control-Allow-Origin": {
                "schema": {
                  "type": "string"
                }
              },
              "Access-Control-Allow-Methods": {
                "schema": {
                  "type": "string"
                }
              },
              "Access-Control-Allow-Headers": {
                "schema": {
                  "type": "string"
                }
              }
            },
            "content": {
              "application/json": {
                "schema": {
                  "$ref": "#/components/schemas/Empty"
                }
              }
            }
          }
        },
        "x-amazon-apigateway-integration": {
          "responses": {
            "default": {
              "statusCode": "200",
              "responseParameters": {
                "method.response.header.Access-Control-Allow-Methods": "'*'",
                "method.response.header.Access-Control-Allow-Headers": "'Content-Type,X-Amz-Date,Authorization,X-Api-Key,X-Amz-Security-Token'",
                "method.response.header.Access-Control-Allow-Origin": "'*'"
              }
            }
          },
          "requestTemplates": {
            "application/json": "{\"statusCode\": 200}"
          },
          "passthroughBehavior": "when_no_match",
          "type": "mock"
        }
      }
    },
    "/tables/{tableId}": {
      "get": {
        "summary": "Retrieve a specific table",
        "description": "This endpoint retrieves details of a specific table identified by its tableId.",
        "parameters": [
          {
            "name": "tableId",
            "in": "path",
            "required": true,
            "schema": {
              "type": "string"
            },
            "description": "The unique identifier of the table"
          }
        ],
        "responses": {
          "200": {
            "description": "Table details retrieved successfully",
            "content": {
              "application/json": {
                "schema": {
                  "$ref": "#/components/schemas/Empty"
                }
              }
            }
          }
        },
        "security": [
          {
            "authorizer": []
          }
        ],
        "x-amazon-apigateway-integration": {
          "httpMethod": "POST",
          "uri": "arn:aws:apigateway:eu-west-1:lambda:path/2015-03-31/functions/arn:aws:lambda:eu-west-1:423623856894:function:api_handler/invocations",
          "responses": {
            "default": {
              "statusCode": "200"
            }
          },
          "passthroughBehavior": "when_no_match",
          "type": "aws_proxy"
        }
      }
    },
    "/signup": {
      "post": {
        "summary": "Register a new user",
        "description": "This endpoint registers a new user by accepting a username and password, creating a new account in the system.",
        "requestBody": {
          "required": true,
          "content": {
            "application/json": {
              "schema": {
                "type": "object",
                "properties": {
                  "username": {
                    "type": "string",
                    "description": "The desired username for the new user"
                  },
                  "password": {
                    "type": "string",
                    "description": "The password for the new user"
                  }
                },
                "required": [
                  "username",
                  "password"
                ]
              }
            }
          }
        },
        "responses": {
          "200": {
            "description": "User registered successfully",
            "headers": {
              "Access-Control-Allow-Origin": {
                "schema": {
                  "type": "string"
                }
              }
            },
            "content": {
              "application/json": {
                "schema": {
                  "$ref": "#/components/schemas/Empty"
                }
              }
            }
          }
        },
        "x-amazon-apigateway-integration": {
          "httpMethod": "POST",
          "uri": "arn:aws:apigateway:eu-west-1:lambda:path/2015-03-31/functions/arn:aws:lambda:eu-west-1:423623856894:function:api_handler/invocations",
          "responses": {
            "default": {
              "statusCode": "200",
              "responseParameters": {
                "method.response.header.Access-Control-Allow-Origin": "'*'"
              }
            }
          },
          "passthroughBehavior": "when_no_match",
          "type": "aws_proxy"
        }
      },
      "options": {
        "summary": "CORS preflight for /signup",
        "description": "Handles CORS preflight requests for the /signup endpoint.",
        "responses": {
          "200": {
            "description": "CORS preflight response",
            "headers": {
              "Access-Control-Allow-Origin": {
                "schema": {
                  "type": "string"
                }
              },
              "Access-Control-Allow-Methods": {
                "schema": {
                  "type": "string"
                }
              },
              "Access-Control-Allow-Headers": {
                "schema": {
                  "type": "string"
                }
              }
            },
            "content": {
              "application/json": {
                "schema": {
                  "$ref": "#/components/schemas/Empty"
                }
              }
            }
          }
        },
        "x-amazon-apigateway-integration": {
          "responses": {
            "default": {
              "statusCode": "200",
              "responseParameters": {
                "method.response.header.Access-Control-Allow-Methods": "'*'",
                "method.response.header.Access-Control-Allow-Headers": "'Content-Type,X-Amz-Date,Authorization,X-Api-Key,X-Amz-Security-Token'",
                "method.response.header.Access-Control-Allow-Origin": "'*'"
              }
            }
          },
          "requestTemplates": {
            "application/json": "{\"statusCode\": 200}"
          },
          "passthroughBehavior": "when_no_match",
          "type": "mock"
        }
      }
    }
  },
  "components": {
    "schemas": {
      "Empty": {
        "title": "Empty Schema",
        "type": "object"
      }
    },
    "securitySchemes": {
      "authorizer": {
        "type": "apiKey",
        "name": "Authorization",
        "in": "header",
        "x-amazon-apigateway-authtype": "cognito_user_pools",
        "x-amazon-apigateway-authorizer": {
          "x-syndicate-cognito-userpool-names": [
            "${booking_userpool}"
          ],
          "type": "cognito_user_pools"
        }
      }
    }
  },
  "x-syndicate-openapi-tags": {
    "run_id": "JAP-12",
    "run_type": "stm",
    "type": "user",
    "user_id": "a7d5d7ab"
  }
}